{
    "actions": [
      {
        "id": "turn_lights_on",
        "label": "Turn lights on",
        "description": "Turn on the ceiling lights in the room."
      },
      {
        "id": "turn_lights_off",
        "label": "Turn lights off",
        "description": "Turn off the ceiling lights in the room."
      },
      {
        "id": "open_curtain_blinds",
        "label": "Open curtain blinds",
        "description": "Open the curtains for the main window."
      },
      {
        "id": "close_curtain_blinds",
        "label": "Close curtain blinds",
        "description": "Close the curtains for the main window."
      }
    ],
    "rules": [
      {
        "id": "rule-1",
        "condition_text": "Someone enters the room",
        "action_id": "turn_lights_on"
      },
      {
        "id": "rule-2",
        "condition_text": "Someone leaves the room.",
        "action_id": "turn_lights_off"
      }
    ]
  }